flexit/__init__.py
flexit/attention.py
flexit/callbacks.py
flexit/configs.py
flexit/core.py
flexit/factory.py
flexit/layers.py
flexit/loss.py
flexit/models.py
flexit/models_heads.py
flexit/pos_embeddings.py
flexit/train.py
flexit/utils.py
flexitransformers-0.2.1.dist-info/licenses/LICENSE
flexitransformers-0.2.1.dist-info/METADATA
flexitransformers-0.2.1.dist-info/WHEEL
flexitransformers-0.2.1.dist-info/top_level.txt
flexitransformers-0.2.1.dist-info/RECORD
