Metadata-Version: 2.4
Name: flexitransformers
Version: 0.2.1
Summary: This repository provides a flexible and modular implementation of the Transformer architecture,
Author-email: Ahmed Elshahawy <aelshahawy78@gmail.com>
License: MIT
Project-URL: Homepage, https://github.com/A-Elshahawy/FlexiTransformers
Project-URL: Bug Tracker, https://github.com/A-Elshahawy/FlexiTransformers/issues
Keywords: transformer,nlp,deep learning,machine learning,attention
Classifier: Development Status :: 4 - Beta
Classifier: Intended Audience :: Developers
Classifier: Intended Audience :: Science/Research
Classifier: License :: OSI Approved :: MIT License
Classifier: Programming Language :: Python :: 3
Classifier: Programming Language :: Python :: 3.10
Classifier: Programming Language :: Python :: 3.11
Classifier: Programming Language :: Python :: 3.12
Classifier: Topic :: Scientific/Engineering :: Artificial Intelligence
Requires-Python: >=3.10
License-File: LICENSE
Requires-Dist: rich>=13.9.4
Requires-Dist: torch>=2.0.1
Requires-Dist: tqdm>=4.67.1
Provides-Extra: dev
Requires-Dist: pytest>=7.0.0; extra == "dev"
Requires-Dist: ruff>=0.3.0; extra == "dev"
Requires-Dist: mypy>=1.9.0; extra == "dev"
Requires-Dist: sphinx>=4.3.0; extra == "dev"
Dynamic: license-file
